{
    "day": "Perjantai 29. elokuuta 2025",
    "entries": [
        { "finnish": "nimipäivä", "chinese": "命名日" },
        { "finnish": "Huomenna on minun pojan nimipäivä. Minun pojan nimi on Eemil.", "chinese": "明天是我儿子的命名日。我儿子的名字是Eemil。" },
        { "finnish": "Hyvää nimipäivää!", "chinese": "命名日快乐！" },
        { "finnish": "Aurinko paistaa ja on kuuma.", "chinese": "阳光明媚而且天气炎热。" },
        { "finnish": "On kylmä ja sataa lunta.", "chinese": "天气寒冷并且在下雪。" },
        { "finnish": "On pilvistä ja kylmä.", "chinese": "多云而且寒冷。" },
        { "finnish": "asteet", "chinese": "度 (温度)" },
        { "finnish": "Katsotaan säätietoja.", "chinese": "我们来看天气预报。" },
        { "finnish": "Kuinka monta astetta ulkona on?", "chinese": "外面多少度？" },
        { "finnish": "Ulkona on +17 astetta.", "chinese": "外面零上17度。" },
        { "finnish": "Kuinka monta astetta sisällä on?", "chinese": "室内多少度？" },
        { "finnish": "En tiedä.", "chinese": "我不知道。" },
        { "finnish": "Sisällä on +21 astetta.", "chinese": "室内零上21度。" },
        { "finnish": "Kuinka monta astetta siellä on?", "chinese": "那里多少度？" },
        { "finnish": "Täällä on +12 astetta.", "chinese": "这里零上12度。" },
        { "finnish": "toisen asteen koulutus", "chinese": "第二级教育 (职业学校/高中)" },
        { "finnish": "toinen aste", "chinese": "第二级" },
        { "finnish": "e > ö (vain huulet muuttuvat, kieli pysyy paikallaan)", "chinese": "e > ö (只有嘴唇变化，舌头保持不动)" },
        { "finnish": "sanelu", "chinese": "听写" },
        { "finnish": "Miten se kirjoitetaan?", "chinese": "这个怎么写？" },
        { "finnish": "Miten sinun etunimi kirjoitetaan?", "chinese": "你的名字怎么拼写？" },
        { "finnish": "Z = tset / tseta", "chinese": "Z = tset / tseta" },
        { "finnish": "I = “ii”", "chinese": "I = “ii”" },
        { "finnish": "J = “jii”", "chinese": "J = “jii”" },
        { "finnish": "Q = “kuu”", "chinese": "Q = “kuu”" },
        { "finnish": "KOTITEHTÄVÄT: Lue vihko (myös vanhat asiat)! Katso videot! Opettele sanoja! Lepää!", "chinese": "家庭作业：读笔记本（也包括旧内容）！看视频！学习单词！休息！" },
        { "finnish": "Kiitos tästä viikosta! Hyvää viikonloppua! Nähdään maanantaina tasan kello 9.00!", "chinese": "感谢本周！周末愉快！我们周一上午9点整见！" },
        { "finnish": "vokaali", "chinese": "元音" },
        { "finnish": "konsonantti", "chinese": "辅音" },
        { "finnish": "Kieli on samassa paikassa, mutta suun asento muuttuu.", "chinese": "舌头在同一个位置，但嘴的姿势改变了。" },
        { "finnish": "delfiini", "chinese": "海豚" },
        { "finnish": "sydän", "chinese": "心脏" },
        { "finnish": "addikti", "chinese": "上瘾者" },
        { "finnish": "addiktio", "chinese": "成瘾" },
        { "finnish": "gaselli", "chinese": "瞪羚" },
        { "finnish": "gorilla", "chinese": "大猩猩" },
        { "finnish": "mango", "chinese": "芒果" },
        { "finnish": "grilli", "chinese": "烧烤架" },
        { "finnish": "greippi", "chinese": "葡萄柚" },
        { "finnish": "saaga", "chinese": "传说" },
        { "finnish": "magneettinen", "chinese": "磁性的" },
        { "finnish": "äng-äänne", "chinese": "ng音" },
        { "finnish": "kenkä", "chinese": "鞋子" },
        { "finnish": "kengät", "chinese": "鞋子 (复数)" },
        { "finnish": "tanko", "chinese": "杆" },
        { "finnish": "tangot", "chinese": "杆 (复数)" },
        { "finnish": "englanti", "chinese": "英语" },
        { "finnish": "rapu", "chinese": "小龙虾, 螃蟹" },
        { "finnish": "lakki", "chinese": "帽子" },
        { "finnish": "jääkaappi", "chinese": "冰箱" },
        { "finnish": "veitsi", "chinese": "刀" },
        { "finnish": "hakata", "chinese": "砍" },
        { "finnish": "hylly", "chinese": "架子" },
        { "finnish": "kysymysmerkki", "chinese": "问号" },
        { "finnish": "tarina", "chinese": "故事" },
        { "finnish": "vaille", "chinese": "差" },
        { "finnish": "kyllä", "chinese": "是" },
        { "finnish": "Ylihuomenna on sunnuntai.", "chinese": "后天是星期天。" },
        { "finnish": "Miten sinun nimi kirjoitetaan?", "chinese": "你的名字怎么写？" }
    ]
}
